llmformat/__init__.py
llmformat/constant.py
llmformat/grammar_builder.py
llmformat/lex_helper.py
llmformat/tokenfilter.py
llmformat/trie.py
llmformat/grammar_files/__init__.py
llmformat/grammar_files/base.bnf
llmformat/grammar_files/grammar_constant.py
llmformat/grammar_files/json.bnf
llmformat/grammar_files/json_min.bnf
llmformat/grammar_files/json_with_intro.bnf
llmformat/larkopt/__init__.py
llmformat/larkopt/lark_parser.py
llmformat/llminterface/__init__.py
llmformat/llminterface/vllm.py
llmformat/tools/__init__.py
llmformat/tools/bnf_writer_helper.py
llmformat/tools/gen_bnf.py
llmformat-0.0.2.1.dist-info/LICENSE
llmformat-0.0.2.1.dist-info/METADATA
llmformat-0.0.2.1.dist-info/WHEEL
llmformat-0.0.2.1.dist-info/top_level.txt
llmformat-0.0.2.1.dist-info/RECORD
