Metadata-Version: 2.1
Name: llmformat
Version: 0.0.2.1
Summary: Format LLM language by using LALR(1) grammar. Supports JSON, XML, etc.
Author: Qiuling Xu
Author-email: Qiuling Xu <xennaughtyboy@gmail.com>
Project-URL: Homepage, https://github.com/qiulingxu/llmformat
Project-URL: Issues, https://github.com/qiulingxu/llmformat/issues
Keywords: python,llm,format,json,regex
Classifier: Programming Language :: Python :: 3
Classifier: License :: OSI Approved :: MIT License
Classifier: Operating System :: OS Independent
Requires-Python: >=3.8
License-File: LICENSE
Requires-Dist: lark >=1.1.8
Requires-Dist: vllm >=0.2.6
